{"_ts":[1577847013,1577935269],"_r":{"breakdown":{"html":{"bytes":[54462,55112],"requests":[30,30]},"js":{"bytes":[1142935,1107383],"requests":[62,62]},"css":{"bytes":[34366,34987],"requests":[9,10]},"image":{"bytes":[1078287,1026543],"requests":[68,69]},"flash":{"bytes":[0,0],"requests":[0,0]},"font":{"bytes":[138072,152680],"requests":[3,4]},"video":{"bytes":[0,0],"requests":[0,0]},"other":{"bytes":[39147,44746],"requests":[44,45]}},"date":[1577847013,1577935269],"domElements":[1031,1031],"domInteractive":[9817,14442],"firstPaint":[8230.5999999953,13447.2000000005],"fullyLoaded":[43761,48167],"id":["200101_WK_b05e8a07575658d13422ea31124caae7","200102_BM_5c1b06dda3d64d714d3093d5108c3f47"],"loadTime":[31563,34524],"render":[8287,13487],"SpeedIndex":[10142,14260],"TTFB":[3715,8903],"videoFrames":[[{"_i":"ms_000000.jpg","_t":0,"_vc":0},{"_i":"ms_008287.jpg","_t":8287,"_vc":63},{"_i":"ms_008629.jpg","_t":8629,"_vc":81},{"_i":"ms_008655.jpg","_t":8655,"_vc":81},{"_i":"ms_008707.jpg","_t":8707,"_vc":81},{"_i":"ms_008750.jpg","_t":8750,"_vc":81},{"_i":"ms_008801.jpg","_t":8801,"_vc":81},{"_i":"ms_008853.jpg","_t":8853,"_vc":81},{"_i":"ms_008887.jpg","_t":8887,"_vc":81},{"_i":"ms_008937.jpg","_t":8937,"_vc":81},{"_i":"ms_010129.jpg","_t":10129,"_vc":93},{"_i":"ms_010431.jpg","_t":10431,"_vc":94},{"_i":"ms_025203.jpg","_t":25203,"_vc":89},{"_i":"ms_025671.jpg","_t":25671,"_vc":89},{"_i":"ms_026638.jpg","_t":26638,"_vc":89},{"_i":"ms_027206.jpg","_t":27206,"_vc":89},{"_i":"ms_027257.jpg","_t":27257,"_vc":89},{"_i":"ms_029393.jpg","_t":29393,"_vc":90},{"_i":"ms_030145.jpg","_t":30145,"_vc":100}],[{"_i":"ms_000000.jpg","_t":0,"_vc":0},{"_i":"ms_013487.jpg","_t":13487,"_vc":87},{"_i":"ms_013524.jpg","_t":13524,"_vc":87},{"_i":"ms_013553.jpg","_t":13553,"_vc":87},{"_i":"ms_013590.jpg","_t":13590,"_vc":86},{"_i":"ms_013620.jpg","_t":13620,"_vc":86},{"_i":"ms_013717.jpg","_t":13717,"_vc":86},{"_i":"ms_013788.jpg","_t":13788,"_vc":86},{"_i":"ms_013863.jpg","_t":13863,"_vc":86},{"_i":"ms_013889.jpg","_t":13889,"_vc":86},{"_i":"ms_014701.jpg","_t":14701,"_vc":97},{"_i":"ms_014994.jpg","_t":14994,"_vc":97},{"_i":"ms_027385.jpg","_t":27385,"_vc":95},{"_i":"ms_030824.jpg","_t":30824,"_vc":95},{"_i":"ms_031144.jpg","_t":31144,"_vc":97},{"_i":"ms_031447.jpg","_t":31447,"_vc":98},{"_i":"ms_032240.jpg","_t":32240,"_vc":98},{"_i":"ms_032780.jpg","_t":32780,"_vc":100},{"_i":"ms_034164.jpg","_t":34164,"_vc":100}]],"visualComplete":[30145,32780],"lighthouse":[30,30],"pagespeed":[54,53]}}