{"_ts":[1494688676,1494868371,1494955520],"_r":{"breakdown":{"html":{"bytes":[108328,109619,114312],"requests":[39,34,41]},"js":{"bytes":[1474886,1442378,1476418],"requests":[93,90,92]},"css":{"bytes":[41564,43563,46029],"requests":[9,12,13]},"image":{"bytes":[811027,733018,778232],"requests":[99,84,96]},"flash":{"bytes":[0,0,0],"requests":[0,0,0]},"font":{"bytes":[241151,270717,271238],"requests":[6,8,8]},"other":{"bytes":[42538,42540,42421],"requests":[18,18,18]}},"date":[1494688676,1494868371,1494955520],"domElements":[1114,1113,1114],"domInteractive":[12317,6806,6749],"firstPaint":[10102,4240,6013],"fullyLoaded":[32445,27748,40243],"id":["170513_KQ_PNE","170515_CK_11BK","170516_9W_13HG"],"loadTime":[28683,23940,37195],"render":[10551,4347,6246],"SpeedIndex":[12151,7239,8813],"TTFB":[7547,2136,3093],"videoFrames":[[{"_i":"frame_0000.jpg","_t":0,"_vc":0},{"_i":"frame_0106.jpg","_t":10600,"_vc":73},{"_i":"frame_0121.jpg","_t":12100,"_vc":65},{"_i":"frame_0147.jpg","_t":14700,"_vc":85},{"_i":"frame_0161.jpg","_t":16100,"_vc":99},{"_i":"frame_0187.jpg","_t":18700,"_vc":100},{"_i":"frame_0220.jpg","_t":22000,"_vc":100}],[{"_i":"frame_0000.jpg","_t":0,"_vc":0},{"_i":"frame_0043.jpg","_t":4300,"_vc":66},{"_i":"frame_0045.jpg","_t":4500,"_vc":66},{"_i":"frame_0047.jpg","_t":4700,"_vc":66},{"_i":"frame_0048.jpg","_t":4800,"_vc":66},{"_i":"frame_0106.jpg","_t":10600,"_vc":92},{"_i":"frame_0118.jpg","_t":11800,"_vc":94},{"_i":"frame_0157.jpg","_t":15700,"_vc":94},{"_i":"frame_0184.jpg","_t":18400,"_vc":94},{"_i":"frame_0226.jpg","_t":22600,"_vc":94},{"_i":"frame_0228.jpg","_t":22800,"_vc":95},{"_i":"frame_0234.jpg","_t":23400,"_vc":98},{"_i":"frame_0235.jpg","_t":23500,"_vc":99},{"_i":"frame_0236.jpg","_t":23600,"_vc":99},{"_i":"frame_0237.jpg","_t":23700,"_vc":99},{"_i":"frame_0240.jpg","_t":24000,"_vc":99},{"_i":"frame_0241.jpg","_t":24100,"_vc":99},{"_i":"frame_0244.jpg","_t":24400,"_vc":100}],[{"_i":"frame_0000.jpg","_t":0,"_vc":0},{"_i":"frame_0062.jpg","_t":6200,"_vc":64},{"_i":"frame_0065.jpg","_t":6500,"_vc":64},{"_i":"frame_0071.jpg","_t":7100,"_vc":68},{"_i":"frame_0073.jpg","_t":7300,"_vc":91},{"_i":"frame_0128.jpg","_t":12800,"_vc":92},{"_i":"frame_0152.jpg","_t":15200,"_vc":92},{"_i":"frame_0180.jpg","_t":18000,"_vc":92},{"_i":"frame_0226.jpg","_t":22600,"_vc":92},{"_i":"frame_0233.jpg","_t":23300,"_vc":94},{"_i":"frame_0235.jpg","_t":23500,"_vc":94},{"_i":"frame_0236.jpg","_t":23600,"_vc":94},{"_i":"frame_0237.jpg","_t":23700,"_vc":94},{"_i":"frame_0239.jpg","_t":23900,"_vc":94},{"_i":"frame_0241.jpg","_t":24100,"_vc":94},{"_i":"frame_0242.jpg","_t":24200,"_vc":94},{"_i":"frame_0244.jpg","_t":24400,"_vc":94},{"_i":"frame_0245.jpg","_t":24500,"_vc":94},{"_i":"frame_0246.jpg","_t":24600,"_vc":94},{"_i":"frame_0248.jpg","_t":24800,"_vc":94},{"_i":"frame_0250.jpg","_t":25000,"_vc":94},{"_i":"frame_0358.jpg","_t":35800,"_vc":92},{"_i":"frame_0366.jpg","_t":36600,"_vc":92},{"_i":"frame_0372.jpg","_t":37200,"_vc":98},{"_i":"frame_0378.jpg","_t":37800,"_vc":99},{"_i":"frame_0383.jpg","_t":38300,"_vc":99},{"_i":"frame_0389.jpg","_t":38900,"_vc":99},{"_i":"frame_0394.jpg","_t":39400,"_vc":100}]],"visualComplete":[18700,24400,39400],"lighthouse":[null,null,null],"pagespeed":[63,61,60]}}