{"_ts":[1493627966],"_r":{"breakdown":{"html":{"bytes":[52957],"requests":[21]},"js":{"bytes":[708978],"requests":[61]},"css":{"bytes":[23575],"requests":[7]},"image":{"bytes":[1361777],"requests":[60]},"flash":{"bytes":[0],"requests":[0]},"font":{"bytes":[162487],"requests":[5]},"other":{"bytes":[8652],"requests":[37]}},"date":[1493627966],"domElements":[1332],"domInteractive":[12472],"firstPaint":[10665],"fullyLoaded":[46167],"id":["170501_8S_F2G"],"loadTime":[31923],"render":[12034],"SpeedIndex":[15019],"TTFB":[1138],"videoFrames":[[{"_i":"ms_000000.jpg","_t":0,"_vc":0},{"_i":"ms_012034.jpg","_t":12034,"_vc":13},{"_i":"ms_012068.jpg","_t":12068,"_vc":5},{"_i":"ms_013216.jpg","_t":13216,"_vc":8},{"_i":"ms_013248.jpg","_t":13248,"_vc":9},{"_i":"ms_013902.jpg","_t":13902,"_vc":11},{"_i":"ms_014288.jpg","_t":14288,"_vc":40},{"_i":"ms_015463.jpg","_t":15463,"_vc":70},{"_i":"ms_015839.jpg","_t":15839,"_vc":99},{"_i":"ms_023745.jpg","_t":23745,"_vc":100}]],"visualComplete":[23745],"lighthouse":[27],"pagespeed":[47]}}