{"_ts":[1530412282,1530456262,1530500499,1530544854,1530588279],"_r":{"breakdown":{"html":{"bytes":[39254,39284,39310,39317,39231],"requests":[15,15,13,13,15]},"js":{"bytes":[843929,844047,844279,842473,847901],"requests":[60,60,60,60,60]},"css":{"bytes":[39468,39104,39405,39155,35347],"requests":[7,7,7,7,7]},"image":{"bytes":[1672677,1682609,1672140,1673539,1664236],"requests":[80,80,79,79,81]},"flash":{"bytes":[0,0,0,0,0],"requests":[0,0,0,0,0]},"font":{"bytes":[168253,168256,168232,168226,168209],"requests":[4,4,4,4,4]},"video":{"bytes":[0,0,0,0,0],"requests":[0,0,0,0,0]},"other":{"bytes":[26180,26142,26115,25419,25421],"requests":[27,27,26,26,28]}},"date":[1530412282,1530456262,1530500499,1530544854,1530588279],"domElements":[1817,1817,1816,1815,1816],"domInteractive":[2093,2470,2252,2270,2213],"firstPaint":[1719.6000000004,2004.3000000005,1928.1999999985,1873.900000006,1786.8000000017],"fullyLoaded":[7667,7677,7497,7525,7545],"id":["180701_HP_2a5d15d67f2b83d8522f40603d7082d5","180701_PA_5b6d8b5eb61d258652e482a4a92a7790","180702_0J_8671156d13b1a736ff1a1a79f0723533","180702_G3_0505e8162fba460af4ec9aface8a9deb","180703_CX_bb4a965e12d2ec73c198180dcee404d2"],"loadTime":[6192,6394,6248,6199,6224],"render":[1800,2100,2000,2000,1900],"SpeedIndex":[5414,5580,5834,6128,4385],"TTFB":[674,960,905,841,759],"videoFrames":[[{"_i":"ms_000000.jpg","_t":0,"_vc":0},{"_i":"ms_001800.jpg","_t":1800,"_vc":12},{"_i":"ms_001900.jpg","_t":1900,"_vc":12},{"_i":"ms_002000.jpg","_t":2000,"_vc":12},{"_i":"ms_002100.jpg","_t":2100,"_vc":14},{"_i":"ms_002200.jpg","_t":2200,"_vc":15},{"_i":"ms_002300.jpg","_t":2300,"_vc":15},{"_i":"ms_002400.jpg","_t":2400,"_vc":15},{"_i":"ms_002500.jpg","_t":2500,"_vc":15},{"_i":"ms_002600.jpg","_t":2600,"_vc":17},{"_i":"ms_002700.jpg","_t":2700,"_vc":17},{"_i":"ms_002800.jpg","_t":2800,"_vc":17},{"_i":"ms_003400.jpg","_t":3400,"_vc":17},{"_i":"ms_003500.jpg","_t":3500,"_vc":38},{"_i":"ms_003600.jpg","_t":3600,"_vc":38},{"_i":"ms_003800.jpg","_t":3800,"_vc":38},{"_i":"ms_004000.jpg","_t":4000,"_vc":38},{"_i":"ms_004400.jpg","_t":4400,"_vc":38},{"_i":"ms_004800.jpg","_t":4800,"_vc":38},{"_i":"ms_004900.jpg","_t":4900,"_vc":38},{"_i":"ms_005100.jpg","_t":5100,"_vc":38},{"_i":"ms_005300.jpg","_t":5300,"_vc":38},{"_i":"ms_005400.jpg","_t":5400,"_vc":38},{"_i":"ms_006300.jpg","_t":6300,"_vc":38},{"_i":"ms_006600.jpg","_t":6600,"_vc":38},{"_i":"ms_006700.jpg","_t":6700,"_vc":38},{"_i":"ms_006800.jpg","_t":6800,"_vc":38},{"_i":"ms_006900.jpg","_t":6900,"_vc":31},{"_i":"ms_007000.jpg","_t":7000,"_vc":100}],[{"_i":"ms_000000.jpg","_t":0,"_vc":0},{"_i":"ms_002100.jpg","_t":2100,"_vc":14},{"_i":"ms_002200.jpg","_t":2200,"_vc":17},{"_i":"ms_002300.jpg","_t":2300,"_vc":18},{"_i":"ms_002400.jpg","_t":2400,"_vc":18},{"_i":"ms_002500.jpg","_t":2500,"_vc":20},{"_i":"ms_002600.jpg","_t":2600,"_vc":20},{"_i":"ms_002700.jpg","_t":2700,"_vc":20},{"_i":"ms_002800.jpg","_t":2800,"_vc":20},{"_i":"ms_002900.jpg","_t":2900,"_vc":20},{"_i":"ms_003100.jpg","_t":3100,"_vc":20},{"_i":"ms_003800.jpg","_t":3800,"_vc":38},{"_i":"ms_003900.jpg","_t":3900,"_vc":38},{"_i":"ms_004000.jpg","_t":4000,"_vc":38},{"_i":"ms_004100.jpg","_t":4100,"_vc":38},{"_i":"ms_004400.jpg","_t":4400,"_vc":38},{"_i":"ms_004500.jpg","_t":4500,"_vc":38},{"_i":"ms_004600.jpg","_t":4600,"_vc":38},{"_i":"ms_004700.jpg","_t":4700,"_vc":38},{"_i":"ms_005300.jpg","_t":5300,"_vc":38},{"_i":"ms_005500.jpg","_t":5500,"_vc":38},{"_i":"ms_005700.jpg","_t":5700,"_vc":38},{"_i":"ms_006100.jpg","_t":6100,"_vc":38},{"_i":"ms_006500.jpg","_t":6500,"_vc":38},{"_i":"ms_006800.jpg","_t":6800,"_vc":38},{"_i":"ms_006900.jpg","_t":6900,"_vc":38},{"_i":"ms_007000.jpg","_t":7000,"_vc":38},{"_i":"ms_007100.jpg","_t":7100,"_vc":39},{"_i":"ms_007200.jpg","_t":7200,"_vc":100}],[{"_i":"ms_000000.jpg","_t":0,"_vc":0},{"_i":"ms_002000.jpg","_t":2000,"_vc":17},{"_i":"ms_002200.jpg","_t":2200,"_vc":19},{"_i":"ms_002400.jpg","_t":2400,"_vc":20},{"_i":"ms_002500.jpg","_t":2500,"_vc":20},{"_i":"ms_002600.jpg","_t":2600,"_vc":20},{"_i":"ms_002700.jpg","_t":2700,"_vc":20},{"_i":"ms_002900.jpg","_t":2900,"_vc":20},{"_i":"ms_003000.jpg","_t":3000,"_vc":20},{"_i":"ms_003100.jpg","_t":3100,"_vc":20},{"_i":"ms_003200.jpg","_t":3200,"_vc":20},{"_i":"ms_003400.jpg","_t":3400,"_vc":20},{"_i":"ms_003600.jpg","_t":3600,"_vc":20},{"_i":"ms_004000.jpg","_t":4000,"_vc":20},{"_i":"ms_004100.jpg","_t":4100,"_vc":20},{"_i":"ms_004200.jpg","_t":4200,"_vc":20},{"_i":"ms_004600.jpg","_t":4600,"_vc":20},{"_i":"ms_005000.jpg","_t":5000,"_vc":20},{"_i":"ms_005100.jpg","_t":5100,"_vc":21},{"_i":"ms_005600.jpg","_t":5600,"_vc":21},{"_i":"ms_005700.jpg","_t":5700,"_vc":21},{"_i":"ms_006100.jpg","_t":6100,"_vc":38},{"_i":"ms_006900.jpg","_t":6900,"_vc":40},{"_i":"ms_007000.jpg","_t":7000,"_vc":100}],[{"_i":"ms_000000.jpg","_t":0,"_vc":0},{"_i":"ms_002000.jpg","_t":2000,"_vc":11},{"_i":"ms_002200.jpg","_t":2200,"_vc":13},{"_i":"ms_002300.jpg","_t":2300,"_vc":13},{"_i":"ms_002400.jpg","_t":2400,"_vc":15},{"_i":"ms_002500.jpg","_t":2500,"_vc":15},{"_i":"ms_002600.jpg","_t":2600,"_vc":15},{"_i":"ms_002700.jpg","_t":2700,"_vc":15},{"_i":"ms_002900.jpg","_t":2900,"_vc":15},{"_i":"ms_003000.jpg","_t":3000,"_vc":15},{"_i":"ms_003100.jpg","_t":3100,"_vc":15},{"_i":"ms_003200.jpg","_t":3200,"_vc":15},{"_i":"ms_003400.jpg","_t":3400,"_vc":15},{"_i":"ms_003600.jpg","_t":3600,"_vc":15},{"_i":"ms_003700.jpg","_t":3700,"_vc":15},{"_i":"ms_003800.jpg","_t":3800,"_vc":15},{"_i":"ms_003900.jpg","_t":3900,"_vc":15},{"_i":"ms_004000.jpg","_t":4000,"_vc":15},{"_i":"ms_004200.jpg","_t":4200,"_vc":15},{"_i":"ms_004300.jpg","_t":4300,"_vc":15},{"_i":"ms_004500.jpg","_t":4500,"_vc":15},{"_i":"ms_004700.jpg","_t":4700,"_vc":15},{"_i":"ms_004900.jpg","_t":4900,"_vc":15},{"_i":"ms_005200.jpg","_t":5200,"_vc":15},{"_i":"ms_005500.jpg","_t":5500,"_vc":15},{"_i":"ms_005700.jpg","_t":5700,"_vc":15},{"_i":"ms_006100.jpg","_t":6100,"_vc":37},{"_i":"ms_007000.jpg","_t":7000,"_vc":36},{"_i":"ms_007100.jpg","_t":7100,"_vc":100}],[{"_i":"ms_000000.jpg","_t":0,"_vc":0},{"_i":"ms_001900.jpg","_t":1900,"_vc":36},{"_i":"ms_002000.jpg","_t":2000,"_vc":36},{"_i":"ms_002100.jpg","_t":2100,"_vc":38},{"_i":"ms_002200.jpg","_t":2200,"_vc":40},{"_i":"ms_002300.jpg","_t":2300,"_vc":40},{"_i":"ms_002400.jpg","_t":2400,"_vc":40},{"_i":"ms_002500.jpg","_t":2500,"_vc":40},{"_i":"ms_002600.jpg","_t":2600,"_vc":40},{"_i":"ms_002700.jpg","_t":2700,"_vc":40},{"_i":"ms_002900.jpg","_t":2900,"_vc":42},{"_i":"ms_003300.jpg","_t":3300,"_vc":42},{"_i":"ms_003800.jpg","_t":3800,"_vc":59},{"_i":"ms_004000.jpg","_t":4000,"_vc":59},{"_i":"ms_004100.jpg","_t":4100,"_vc":59},{"_i":"ms_004300.jpg","_t":4300,"_vc":59},{"_i":"ms_004400.jpg","_t":4400,"_vc":59},{"_i":"ms_004600.jpg","_t":4600,"_vc":59},{"_i":"ms_004800.jpg","_t":4800,"_vc":59},{"_i":"ms_005200.jpg","_t":5200,"_vc":59},{"_i":"ms_005300.jpg","_t":5300,"_vc":59},{"_i":"ms_005400.jpg","_t":5400,"_vc":59},{"_i":"ms_005500.jpg","_t":5500,"_vc":59},{"_i":"ms_005700.jpg","_t":5700,"_vc":59},{"_i":"ms_006300.jpg","_t":6300,"_vc":59},{"_i":"ms_006700.jpg","_t":6700,"_vc":59},{"_i":"ms_006800.jpg","_t":6800,"_vc":59},{"_i":"ms_007000.jpg","_t":7000,"_vc":59},{"_i":"ms_007100.jpg","_t":7100,"_vc":100}]],"visualComplete":[7000,7200,7000,7100,7100],"lighthouse":[31,31,31,31,31],"pagespeed":[69,72,69,71,73]}}