{"_ts":[1496332212,1496362141],"_r":{"breakdown":{"html":{"bytes":[47717,42581],"requests":[26,18]},"js":{"bytes":[952628,980283],"requests":[61,61]},"css":{"bytes":[25523,25667],"requests":[7,7]},"image":{"bytes":[2760656,2776906],"requests":[141,145]},"flash":{"bytes":[0,0],"requests":[0,0]},"font":{"bytes":[170071,170066],"requests":[4,4]},"other":{"bytes":[48891,48362],"requests":[14,13]}},"date":[1496332212,1496362141],"domElements":[2787,2788],"domInteractive":[5299,4992],"firstPaint":[4744,4687],"fullyLoaded":[23218,23291],"id":["170601_5E_R50","170602_D7_RA"],"loadTime":[17572,16998],"render":[4963,4952],"SpeedIndex":[6737,7876],"TTFB":[1996,1875],"videoFrames":[[{"_i":"frame_0000.jpg","_t":0,"_vc":0},{"_i":"frame_0050.jpg","_t":5000,"_vc":80},{"_i":"frame_0054.jpg","_t":5400,"_vc":80},{"_i":"frame_0076.jpg","_t":7600,"_vc":80},{"_i":"frame_0115.jpg","_t":11500,"_vc":91},{"_i":"frame_0127.jpg","_t":12700,"_vc":91},{"_i":"frame_0150.jpg","_t":15000,"_vc":95},{"_i":"frame_0157.jpg","_t":15700,"_vc":98},{"_i":"frame_0166.jpg","_t":16600,"_vc":99},{"_i":"frame_0171.jpg","_t":17100,"_vc":99},{"_i":"frame_0209.jpg","_t":20900,"_vc":99},{"_i":"frame_0235.jpg","_t":23500,"_vc":100}],[{"_i":"frame_0000.jpg","_t":0,"_vc":0},{"_i":"frame_0050.jpg","_t":5000,"_vc":71},{"_i":"frame_0052.jpg","_t":5200,"_vc":71},{"_i":"frame_0073.jpg","_t":7300,"_vc":72},{"_i":"frame_0122.jpg","_t":12200,"_vc":81},{"_i":"frame_0130.jpg","_t":13000,"_vc":81},{"_i":"frame_0154.jpg","_t":15400,"_vc":85},{"_i":"frame_0159.jpg","_t":15900,"_vc":86},{"_i":"frame_0169.jpg","_t":16900,"_vc":86},{"_i":"frame_0170.jpg","_t":17000,"_vc":100}]],"visualComplete":[23500,17000],"lighthouse":[null,null],"pagespeed":[62,64]}}