{"_ts":[1519878886,1519922766],"_r":{"breakdown":{"html":{"bytes":[45770,33741],"requests":[22,19]},"js":{"bytes":[896122,512314],"requests":[82,50]},"css":{"bytes":[127675,36594],"requests":[9,7]},"image":{"bytes":[1576152,1268124],"requests":[122,81]},"flash":{"bytes":[0,0],"requests":[0,0]},"font":{"bytes":[175591,175606],"requests":[6,6]},"video":{"bytes":[0,0],"requests":[0,0]},"other":{"bytes":[73533,69486],"requests":[40,36]}},"date":[1519878886,1519922766],"domElements":[1525,1367],"domInteractive":[9240,19440],"firstPaint":[6988.9000002295,6882.6000001281],"fullyLoaded":[35463,34169],"id":["180301_0T_5fd36eee06fb84af92e90af71addc52b","180301_GS_58398a64a2c4579689bcd4921f2b60ef"],"loadTime":[21778,28070],"render":[7200,7203],"SpeedIndex":[9679,9705],"TTFB":[3391,3189],"videoFrames":[[{"_i":"ms_000000.jpg","_t":0,"_vc":0},{"_i":"ms_007200.jpg","_t":7200,"_vc":5},{"_i":"ms_007470.jpg","_t":7470,"_vc":25},{"_i":"ms_007552.jpg","_t":7552,"_vc":25},{"_i":"ms_007887.jpg","_t":7887,"_vc":25},{"_i":"ms_008276.jpg","_t":8276,"_vc":25},{"_i":"ms_010211.jpg","_t":10211,"_vc":74},{"_i":"ms_010856.jpg","_t":10856,"_vc":100},{"_i":"ms_011659.jpg","_t":11659,"_vc":100}],[{"_i":"ms_000000.jpg","_t":0,"_vc":0},{"_i":"ms_007203.jpg","_t":7203,"_vc":25},{"_i":"ms_007237.jpg","_t":7237,"_vc":25},{"_i":"ms_007462.jpg","_t":7462,"_vc":25},{"_i":"ms_007513.jpg","_t":7513,"_vc":25},{"_i":"ms_008303.jpg","_t":8303,"_vc":25},{"_i":"ms_010138.jpg","_t":10138,"_vc":61},{"_i":"ms_010911.jpg","_t":10911,"_vc":100},{"_i":"ms_020663.jpg","_t":20663,"_vc":100}]],"visualComplete":[10856,10911],"lighthouse":[36,36],"pagespeed":[48,48]}}