{"_ts":[1551411458],"_r":{"breakdown":{"html":{"bytes":[42092],"requests":[28]},"js":{"bytes":[1146407],"requests":[75]},"css":{"bytes":[51331],"requests":[10]},"image":{"bytes":[964671],"requests":[94]},"flash":{"bytes":[0],"requests":[0]},"font":{"bytes":[164924],"requests":[5]},"video":{"bytes":[0],"requests":[0]},"other":{"bytes":[24985],"requests":[29]}},"date":[1551411458],"domElements":[1181],"domInteractive":[11432],"firstPaint":[10104.9000000021],"fullyLoaded":[10170],"id":["190301_0Y_eb8686d42636118116608287d4f08412"],"loadTime":[10170],"render":[10170],"SpeedIndex":[10170],"TTFB":[4576],"videoFrames":[[{"_i":"ms_000000.jpg","_t":0,"_vc":0},{"_i":"ms_010170.jpg","_t":10170,"_vc":100}]],"visualComplete":[10170],"lighthouse":[31],"pagespeed":[57]}}