{"_ts":[1525148789,1525236232,1525280473],"_r":{"breakdown":{"html":{"bytes":[124178,0,125916],"requests":[21,0,21]},"js":{"bytes":[617884,0,601290],"requests":[38,0,37]},"css":{"bytes":[9317,1221,9322],"requests":[3,1,3]},"image":{"bytes":[519516,7485,549729],"requests":[39,1,38]},"flash":{"bytes":[0,0,0],"requests":[0,0,0]},"font":{"bytes":[220071,46599,220068],"requests":[5,3,5]},"video":{"bytes":[0,0,0],"requests":[0,0,0]},"other":{"bytes":[124914,2754,126487],"requests":[22,2,22]}},"date":[1525148789,1525236232,1525280473],"domElements":[7989,null,8112],"domInteractive":[4269,null,4474],"firstPaint":[3330.6999999986,null,3365.9000000007],"fullyLoaded":[11643,null,11814],"id":["180501_FF_524640c4b2e3f3a1f2bd5f1575c37989","180502_ZY_772e4a727a01161a861e913175f12640","180502_BE_e92725e39b83692268efef7df4ab776f"],"loadTime":[9789,null,9997],"render":[3500,null,3600],"SpeedIndex":[5609,null,5675],"TTFB":[2253,null,2274],"videoFrames":[[{"_i":"ms_000000.jpg","_t":0,"_vc":0},{"_i":"ms_003500.jpg","_t":3500,"_vc":67},{"_i":"ms_003600.jpg","_t":3600,"_vc":67},{"_i":"ms_003700.jpg","_t":3700,"_vc":67},{"_i":"ms_003800.jpg","_t":3800,"_vc":67},{"_i":"ms_004100.jpg","_t":4100,"_vc":60},{"_i":"ms_004200.jpg","_t":4200,"_vc":60},{"_i":"ms_004300.jpg","_t":4300,"_vc":67},{"_i":"ms_004700.jpg","_t":4700,"_vc":67},{"_i":"ms_004800.jpg","_t":4800,"_vc":67},{"_i":"ms_004900.jpg","_t":4900,"_vc":67},{"_i":"ms_005000.jpg","_t":5000,"_vc":68},{"_i":"ms_005500.jpg","_t":5500,"_vc":68},{"_i":"ms_005700.jpg","_t":5700,"_vc":63},{"_i":"ms_005800.jpg","_t":5800,"_vc":63},{"_i":"ms_006000.jpg","_t":6000,"_vc":63},{"_i":"ms_007000.jpg","_t":7000,"_vc":63},{"_i":"ms_007800.jpg","_t":7800,"_vc":63},{"_i":"ms_007900.jpg","_t":7900,"_vc":63},{"_i":"ms_008000.jpg","_t":8000,"_vc":63},{"_i":"ms_008300.jpg","_t":8300,"_vc":63},{"_i":"ms_008800.jpg","_t":8800,"_vc":63},{"_i":"ms_008900.jpg","_t":8900,"_vc":63},{"_i":"ms_009000.jpg","_t":9000,"_vc":63},{"_i":"ms_009400.jpg","_t":9400,"_vc":99},{"_i":"ms_010000.jpg","_t":10000,"_vc":99},{"_i":"ms_010100.jpg","_t":10100,"_vc":100}],[{"_i":"ms_000000.jpg","_t":0,"_vc":100}],[{"_i":"ms_000000.jpg","_t":0,"_vc":0},{"_i":"ms_003600.jpg","_t":3600,"_vc":67},{"_i":"ms_003700.jpg","_t":3700,"_vc":68},{"_i":"ms_004000.jpg","_t":4000,"_vc":60},{"_i":"ms_004200.jpg","_t":4200,"_vc":67},{"_i":"ms_004500.jpg","_t":4500,"_vc":67},{"_i":"ms_004700.jpg","_t":4700,"_vc":67},{"_i":"ms_005100.jpg","_t":5100,"_vc":67},{"_i":"ms_005300.jpg","_t":5300,"_vc":67},{"_i":"ms_005400.jpg","_t":5400,"_vc":67},{"_i":"ms_005500.jpg","_t":5500,"_vc":70},{"_i":"ms_005700.jpg","_t":5700,"_vc":64},{"_i":"ms_006000.jpg","_t":6000,"_vc":64},{"_i":"ms_007000.jpg","_t":7000,"_vc":64},{"_i":"ms_007500.jpg","_t":7500,"_vc":64},{"_i":"ms_008000.jpg","_t":8000,"_vc":64},{"_i":"ms_008100.jpg","_t":8100,"_vc":64},{"_i":"ms_008200.jpg","_t":8200,"_vc":63},{"_i":"ms_008500.jpg","_t":8500,"_vc":64},{"_i":"ms_009300.jpg","_t":9300,"_vc":64},{"_i":"ms_009400.jpg","_t":9400,"_vc":63},{"_i":"ms_009500.jpg","_t":9500,"_vc":99},{"_i":"ms_010000.jpg","_t":10000,"_vc":100}]],"visualComplete":[10100,null,10000],"lighthouse":[54,null,54],"pagespeed":[75,75,75]}}