{"_ts":[1509509737,1509553083,1509597023,1509641079,1509684342],"_r":{"breakdown":{"html":{"bytes":[46431,46530,44753,46445,46429],"requests":[23,26,22,23,23]},"js":{"bytes":[1356220,1373813,1356009,1356070,1357068],"requests":[75,77,77,77,77]},"css":{"bytes":[30425,32264,32264,31883,30425],"requests":[6,6,6,6,6]},"image":{"bytes":[3503895,3536421,3466082,3522620,3547653],"requests":[127,129,121,128,122]},"flash":{"bytes":[0,0,0,0,0],"requests":[0,0,0,0,0]},"font":{"bytes":[191392,191392,191401,191383,191401],"requests":[5,5,5,5,5]},"video":{"bytes":[0,0,0,0,0],"requests":[0,0,0,0,0]},"other":{"bytes":[28596,28597,28598,28600,28594],"requests":[47,47,46,45,45]}},"date":[1509509737,1509553083,1509597023,1509641079,1509684342],"domElements":[1531,1533,1532,1532,1532],"domInteractive":[4911,3900,5862,3914,4336],"firstPaint":[4655,3276,5720,3706,4049],"fullyLoaded":[14887,14057,15313,14224,13330],"id":["171101_Q8_30cd21906dc59a04f18e21d39a32ae6a","171101_24_acedf09be4ef626d899dffd5a6372794","171102_S8_6e515e79861d1c8d6e92e33ffa1e0f8a","171102_AP_d36d2bc2ac6f49fc16c31617a2194e05","171103_G1_0d9c3c5d302153c2566f76f517281f61"],"loadTime":[9341,11113,10836,8667,9214],"render":[4767,3367,5967,3833,4133],"SpeedIndex":[6089,5008,7455,5273,5740],"TTFB":[1018,426,1954,285,202],"videoFrames":[[{"_i":"ms_000000.jpg","_t":0,"_vc":0},{"_i":"ms_004767.jpg","_t":4767,"_vc":64},{"_i":"ms_004867.jpg","_t":4867,"_vc":65},{"_i":"ms_005200.jpg","_t":5200,"_vc":69},{"_i":"ms_005267.jpg","_t":5267,"_vc":71},{"_i":"ms_005400.jpg","_t":5400,"_vc":71},{"_i":"ms_005467.jpg","_t":5467,"_vc":71},{"_i":"ms_005500.jpg","_t":5500,"_vc":70},{"_i":"ms_005533.jpg","_t":5533,"_vc":70},{"_i":"ms_006033.jpg","_t":6033,"_vc":70},{"_i":"ms_006067.jpg","_t":6067,"_vc":70},{"_i":"ms_006467.jpg","_t":6467,"_vc":70},{"_i":"ms_006833.jpg","_t":6833,"_vc":70},{"_i":"ms_007300.jpg","_t":7300,"_vc":64},{"_i":"ms_007600.jpg","_t":7600,"_vc":64},{"_i":"ms_007833.jpg","_t":7833,"_vc":64},{"_i":"ms_008067.jpg","_t":8067,"_vc":64},{"_i":"ms_008200.jpg","_t":8200,"_vc":68},{"_i":"ms_008333.jpg","_t":8333,"_vc":68},{"_i":"ms_008833.jpg","_t":8833,"_vc":99},{"_i":"ms_008867.jpg","_t":8867,"_vc":100},{"_i":"ms_008900.jpg","_t":8900,"_vc":100},{"_i":"ms_008967.jpg","_t":8967,"_vc":100},{"_i":"ms_009000.jpg","_t":9000,"_vc":100},{"_i":"ms_009033.jpg","_t":9033,"_vc":100},{"_i":"ms_009600.jpg","_t":9600,"_vc":100},{"_i":"ms_009867.jpg","_t":9867,"_vc":99},{"_i":"ms_010100.jpg","_t":10100,"_vc":99},{"_i":"ms_010333.jpg","_t":10333,"_vc":99},{"_i":"ms_010600.jpg","_t":10600,"_vc":99},{"_i":"ms_010867.jpg","_t":10867,"_vc":99},{"_i":"ms_011367.jpg","_t":11367,"_vc":100},{"_i":"ms_011400.jpg","_t":11400,"_vc":100}],[{"_i":"ms_000000.jpg","_t":0,"_vc":0},{"_i":"ms_003367.jpg","_t":3367,"_vc":64},{"_i":"ms_003400.jpg","_t":3400,"_vc":64},{"_i":"ms_003600.jpg","_t":3600,"_vc":64},{"_i":"ms_003667.jpg","_t":3667,"_vc":64},{"_i":"ms_003767.jpg","_t":3767,"_vc":65},{"_i":"ms_003867.jpg","_t":3867,"_vc":69},{"_i":"ms_004033.jpg","_t":4033,"_vc":69},{"_i":"ms_004067.jpg","_t":4067,"_vc":71},{"_i":"ms_004100.jpg","_t":4100,"_vc":71},{"_i":"ms_004367.jpg","_t":4367,"_vc":71},{"_i":"ms_004500.jpg","_t":4500,"_vc":71},{"_i":"ms_004567.jpg","_t":4567,"_vc":71},{"_i":"ms_004600.jpg","_t":4600,"_vc":71},{"_i":"ms_004633.jpg","_t":4633,"_vc":70},{"_i":"ms_004667.jpg","_t":4667,"_vc":70},{"_i":"ms_004733.jpg","_t":4733,"_vc":70},{"_i":"ms_004967.jpg","_t":4967,"_vc":70},{"_i":"ms_005467.jpg","_t":5467,"_vc":70},{"_i":"ms_006333.jpg","_t":6333,"_vc":70},{"_i":"ms_006500.jpg","_t":6500,"_vc":63},{"_i":"ms_006767.jpg","_t":6767,"_vc":64},{"_i":"ms_006967.jpg","_t":6967,"_vc":64},{"_i":"ms_007033.jpg","_t":7033,"_vc":64},{"_i":"ms_007533.jpg","_t":7533,"_vc":68},{"_i":"ms_008067.jpg","_t":8067,"_vc":68},{"_i":"ms_008100.jpg","_t":8100,"_vc":68},{"_i":"ms_008133.jpg","_t":8133,"_vc":68},{"_i":"ms_008200.jpg","_t":8200,"_vc":68},{"_i":"ms_008233.jpg","_t":8233,"_vc":67},{"_i":"ms_008333.jpg","_t":8333,"_vc":99},{"_i":"ms_008600.jpg","_t":8600,"_vc":99},{"_i":"ms_009033.jpg","_t":9033,"_vc":99},{"_i":"ms_009267.jpg","_t":9267,"_vc":99},{"_i":"ms_009533.jpg","_t":9533,"_vc":99},{"_i":"ms_009767.jpg","_t":9767,"_vc":99},{"_i":"ms_010033.jpg","_t":10033,"_vc":99},{"_i":"ms_011167.jpg","_t":11167,"_vc":99},{"_i":"ms_011300.jpg","_t":11300,"_vc":99},{"_i":"ms_011533.jpg","_t":11533,"_vc":99},{"_i":"ms_011800.jpg","_t":11800,"_vc":99},{"_i":"ms_012033.jpg","_t":12033,"_vc":99},{"_i":"ms_012300.jpg","_t":12300,"_vc":99},{"_i":"ms_012800.jpg","_t":12800,"_vc":100},{"_i":"ms_012867.jpg","_t":12867,"_vc":100}],[{"_i":"ms_000000.jpg","_t":0,"_vc":0},{"_i":"ms_005967.jpg","_t":5967,"_vc":64},{"_i":"ms_006300.jpg","_t":6300,"_vc":69},{"_i":"ms_006400.jpg","_t":6400,"_vc":71},{"_i":"ms_006433.jpg","_t":6433,"_vc":71},{"_i":"ms_006467.jpg","_t":6467,"_vc":71},{"_i":"ms_006533.jpg","_t":6533,"_vc":70},{"_i":"ms_006967.jpg","_t":6967,"_vc":70},{"_i":"ms_007167.jpg","_t":7167,"_vc":70},{"_i":"ms_007600.jpg","_t":7600,"_vc":70},{"_i":"ms_007633.jpg","_t":7633,"_vc":70},{"_i":"ms_008333.jpg","_t":8333,"_vc":64},{"_i":"ms_008600.jpg","_t":8600,"_vc":64},{"_i":"ms_008733.jpg","_t":8733,"_vc":64},{"_i":"ms_008833.jpg","_t":8833,"_vc":64},{"_i":"ms_009100.jpg","_t":9100,"_vc":64},{"_i":"ms_009233.jpg","_t":9233,"_vc":66},{"_i":"ms_009333.jpg","_t":9333,"_vc":66},{"_i":"ms_009900.jpg","_t":9900,"_vc":66},{"_i":"ms_009933.jpg","_t":9933,"_vc":66},{"_i":"ms_009967.jpg","_t":9967,"_vc":66},{"_i":"ms_010033.jpg","_t":10033,"_vc":65},{"_i":"ms_010067.jpg","_t":10067,"_vc":65},{"_i":"ms_010233.jpg","_t":10233,"_vc":84},{"_i":"ms_010733.jpg","_t":10733,"_vc":100},{"_i":"ms_011100.jpg","_t":11100,"_vc":100},{"_i":"ms_011367.jpg","_t":11367,"_vc":99},{"_i":"ms_011600.jpg","_t":11600,"_vc":99},{"_i":"ms_011867.jpg","_t":11867,"_vc":99},{"_i":"ms_012100.jpg","_t":12100,"_vc":99},{"_i":"ms_012667.jpg","_t":12667,"_vc":100},{"_i":"ms_012733.jpg","_t":12733,"_vc":100}],[{"_i":"ms_000000.jpg","_t":0,"_vc":0},{"_i":"ms_003833.jpg","_t":3833,"_vc":64},{"_i":"ms_004133.jpg","_t":4133,"_vc":69},{"_i":"ms_004233.jpg","_t":4233,"_vc":70},{"_i":"ms_004533.jpg","_t":4533,"_vc":70},{"_i":"ms_005233.jpg","_t":5233,"_vc":70},{"_i":"ms_005600.jpg","_t":5600,"_vc":70},{"_i":"ms_005967.jpg","_t":5967,"_vc":70},{"_i":"ms_006033.jpg","_t":6033,"_vc":70},{"_i":"ms_006400.jpg","_t":6400,"_vc":63},{"_i":"ms_006933.jpg","_t":6933,"_vc":63},{"_i":"ms_007033.jpg","_t":7033,"_vc":64},{"_i":"ms_007300.jpg","_t":7300,"_vc":64},{"_i":"ms_007500.jpg","_t":7500,"_vc":68},{"_i":"ms_007533.jpg","_t":7533,"_vc":68},{"_i":"ms_008100.jpg","_t":8100,"_vc":68},{"_i":"ms_008133.jpg","_t":8133,"_vc":68},{"_i":"ms_008167.jpg","_t":8167,"_vc":68},{"_i":"ms_008200.jpg","_t":8200,"_vc":68},{"_i":"ms_008233.jpg","_t":8233,"_vc":100},{"_i":"ms_008267.jpg","_t":8267,"_vc":100},{"_i":"ms_009033.jpg","_t":9033,"_vc":99},{"_i":"ms_009333.jpg","_t":9333,"_vc":99},{"_i":"ms_009567.jpg","_t":9567,"_vc":99},{"_i":"ms_009833.jpg","_t":9833,"_vc":99},{"_i":"ms_010067.jpg","_t":10067,"_vc":99},{"_i":"ms_010467.jpg","_t":10467,"_vc":100},{"_i":"ms_010533.jpg","_t":10533,"_vc":100}],[{"_i":"ms_000000.jpg","_t":0,"_vc":0},{"_i":"ms_004133.jpg","_t":4133,"_vc":57},{"_i":"ms_004267.jpg","_t":4267,"_vc":58},{"_i":"ms_004333.jpg","_t":4333,"_vc":66},{"_i":"ms_004500.jpg","_t":4500,"_vc":66},{"_i":"ms_004533.jpg","_t":4533,"_vc":69},{"_i":"ms_004667.jpg","_t":4667,"_vc":69},{"_i":"ms_004833.jpg","_t":4833,"_vc":71},{"_i":"ms_004867.jpg","_t":4867,"_vc":71},{"_i":"ms_004900.jpg","_t":4900,"_vc":71},{"_i":"ms_004967.jpg","_t":4967,"_vc":71},{"_i":"ms_005000.jpg","_t":5000,"_vc":70},{"_i":"ms_005367.jpg","_t":5367,"_vc":70},{"_i":"ms_005867.jpg","_t":5867,"_vc":70},{"_i":"ms_006067.jpg","_t":6067,"_vc":70},{"_i":"ms_006100.jpg","_t":6100,"_vc":70},{"_i":"ms_006800.jpg","_t":6800,"_vc":71},{"_i":"ms_006833.jpg","_t":6833,"_vc":64},{"_i":"ms_007067.jpg","_t":7067,"_vc":64},{"_i":"ms_007300.jpg","_t":7300,"_vc":64},{"_i":"ms_007433.jpg","_t":7433,"_vc":64},{"_i":"ms_007567.jpg","_t":7567,"_vc":64},{"_i":"ms_007900.jpg","_t":7900,"_vc":66},{"_i":"ms_008100.jpg","_t":8100,"_vc":66},{"_i":"ms_008133.jpg","_t":8133,"_vc":66},{"_i":"ms_008167.jpg","_t":8167,"_vc":66},{"_i":"ms_008200.jpg","_t":8200,"_vc":66},{"_i":"ms_008267.jpg","_t":8267,"_vc":65},{"_i":"ms_008933.jpg","_t":8933,"_vc":96},{"_i":"ms_009100.jpg","_t":9100,"_vc":100},{"_i":"ms_009567.jpg","_t":9567,"_vc":99},{"_i":"ms_009800.jpg","_t":9800,"_vc":99},{"_i":"ms_010067.jpg","_t":10067,"_vc":99},{"_i":"ms_010300.jpg","_t":10300,"_vc":99},{"_i":"ms_010567.jpg","_t":10567,"_vc":99},{"_i":"ms_011033.jpg","_t":11033,"_vc":100},{"_i":"ms_011067.jpg","_t":11067,"_vc":100}]],"visualComplete":[8867,12800,10733,8233,9100],"lighthouse":[45,45,45,54,45],"pagespeed":[29,29,29,29,29]}}