{"_ts":[1559354853,1559397994],"_r":{"breakdown":{"html":{"bytes":[42843,59168],"requests":[23,32]},"js":{"bytes":[1070326,1071356],"requests":[63,68]},"css":{"bytes":[43472,42220],"requests":[9,7]},"image":{"bytes":[918254,868129],"requests":[101,110]},"flash":{"bytes":[0,0],"requests":[0,0]},"font":{"bytes":[151264,151264],"requests":[4,4]},"video":{"bytes":[0,0],"requests":[0,0]},"other":{"bytes":[67191,66824],"requests":[31,39]}},"date":[1559354853,1559397994],"domElements":[2182,2185],"domInteractive":[6820,8773],"firstPaint":[6275.9000000005,7015.1999999944],"fullyLoaded":[30681,36154],"id":["190601_9X_4ba0b33c1f1a034d26fe183b8db8b99a","190601_TT_dd9af5e15fbe01f95effccd5e3afc996"],"loadTime":[24339,29860],"render":[6690,7435],"SpeedIndex":[7109,9042],"TTFB":[2136,2870],"videoFrames":[[{"_i":"ms_000000.jpg","_t":0,"_vc":0},{"_i":"ms_006690.jpg","_t":6690,"_vc":96},{"_i":"ms_006712.jpg","_t":6712,"_vc":95},{"_i":"ms_006767.jpg","_t":6767,"_vc":95},{"_i":"ms_006806.jpg","_t":6806,"_vc":95},{"_i":"ms_006862.jpg","_t":6862,"_vc":95},{"_i":"ms_006879.jpg","_t":6879,"_vc":95},{"_i":"ms_006939.jpg","_t":6939,"_vc":95},{"_i":"ms_006992.jpg","_t":6992,"_vc":95},{"_i":"ms_007031.jpg","_t":7031,"_vc":97},{"_i":"ms_007124.jpg","_t":7124,"_vc":97},{"_i":"ms_007538.jpg","_t":7538,"_vc":97},{"_i":"ms_007605.jpg","_t":7605,"_vc":97},{"_i":"ms_007704.jpg","_t":7704,"_vc":97},{"_i":"ms_007824.jpg","_t":7824,"_vc":97},{"_i":"ms_007901.jpg","_t":7901,"_vc":97},{"_i":"ms_008004.jpg","_t":8004,"_vc":97},{"_i":"ms_008118.jpg","_t":8118,"_vc":97},{"_i":"ms_008298.jpg","_t":8298,"_vc":97},{"_i":"ms_008397.jpg","_t":8397,"_vc":97},{"_i":"ms_008562.jpg","_t":8562,"_vc":97},{"_i":"ms_008859.jpg","_t":8859,"_vc":97},{"_i":"ms_008958.jpg","_t":8958,"_vc":97},{"_i":"ms_009057.jpg","_t":9057,"_vc":97},{"_i":"ms_009156.jpg","_t":9156,"_vc":97},{"_i":"ms_009256.jpg","_t":9256,"_vc":97},{"_i":"ms_009355.jpg","_t":9355,"_vc":97},{"_i":"ms_009455.jpg","_t":9455,"_vc":97},{"_i":"ms_009569.jpg","_t":9569,"_vc":97},{"_i":"ms_009669.jpg","_t":9669,"_vc":97},{"_i":"ms_009768.jpg","_t":9768,"_vc":97},{"_i":"ms_009851.jpg","_t":9851,"_vc":97},{"_i":"ms_009949.jpg","_t":9949,"_vc":97},{"_i":"ms_010048.jpg","_t":10048,"_vc":97},{"_i":"ms_010148.jpg","_t":10148,"_vc":97},{"_i":"ms_010247.jpg","_t":10247,"_vc":97},{"_i":"ms_010346.jpg","_t":10346,"_vc":97},{"_i":"ms_010446.jpg","_t":10446,"_vc":97},{"_i":"ms_010545.jpg","_t":10545,"_vc":97},{"_i":"ms_010666.jpg","_t":10666,"_vc":97},{"_i":"ms_010753.jpg","_t":10753,"_vc":97},{"_i":"ms_010911.jpg","_t":10911,"_vc":97},{"_i":"ms_011052.jpg","_t":11052,"_vc":97},{"_i":"ms_011160.jpg","_t":11160,"_vc":97},{"_i":"ms_011266.jpg","_t":11266,"_vc":97},{"_i":"ms_011351.jpg","_t":11351,"_vc":97},{"_i":"ms_011475.jpg","_t":11475,"_vc":97},{"_i":"ms_011563.jpg","_t":11563,"_vc":97},{"_i":"ms_011652.jpg","_t":11652,"_vc":97},{"_i":"ms_012051.jpg","_t":12051,"_vc":97},{"_i":"ms_012543.jpg","_t":12543,"_vc":97},{"_i":"ms_013051.jpg","_t":13051,"_vc":97},{"_i":"ms_013561.jpg","_t":13561,"_vc":97},{"_i":"ms_014050.jpg","_t":14050,"_vc":97},{"_i":"ms_014542.jpg","_t":14542,"_vc":97},{"_i":"ms_015055.jpg","_t":15055,"_vc":97},{"_i":"ms_015579.jpg","_t":15579,"_vc":97},{"_i":"ms_016052.jpg","_t":16052,"_vc":97},{"_i":"ms_016557.jpg","_t":16557,"_vc":95},{"_i":"ms_017053.jpg","_t":17053,"_vc":95},{"_i":"ms_018025.jpg","_t":18025,"_vc":97},{"_i":"ms_019084.jpg","_t":19084,"_vc":99},{"_i":"ms_020291.jpg","_t":20291,"_vc":100}],[{"_i":"ms_000000.jpg","_t":0,"_vc":0},{"_i":"ms_007435.jpg","_t":7435,"_vc":86},{"_i":"ms_007459.jpg","_t":7459,"_vc":85},{"_i":"ms_007532.jpg","_t":7532,"_vc":85},{"_i":"ms_007568.jpg","_t":7568,"_vc":85},{"_i":"ms_007622.jpg","_t":7622,"_vc":85},{"_i":"ms_007657.jpg","_t":7657,"_vc":85},{"_i":"ms_007713.jpg","_t":7713,"_vc":85},{"_i":"ms_007771.jpg","_t":7771,"_vc":85},{"_i":"ms_007861.jpg","_t":7861,"_vc":88},{"_i":"ms_007912.jpg","_t":7912,"_vc":89},{"_i":"ms_008206.jpg","_t":8206,"_vc":89},{"_i":"ms_008305.jpg","_t":8305,"_vc":89},{"_i":"ms_008966.jpg","_t":8966,"_vc":92},{"_i":"ms_009048.jpg","_t":9048,"_vc":92},{"_i":"ms_009281.jpg","_t":9281,"_vc":92},{"_i":"ms_009346.jpg","_t":9346,"_vc":92},{"_i":"ms_009535.jpg","_t":9535,"_vc":92},{"_i":"ms_009725.jpg","_t":9725,"_vc":92},{"_i":"ms_009808.jpg","_t":9808,"_vc":92},{"_i":"ms_009957.jpg","_t":9957,"_vc":92},{"_i":"ms_010042.jpg","_t":10042,"_vc":93},{"_i":"ms_010155.jpg","_t":10155,"_vc":93},{"_i":"ms_010270.jpg","_t":10270,"_vc":93},{"_i":"ms_010353.jpg","_t":10353,"_vc":93},{"_i":"ms_010453.jpg","_t":10453,"_vc":93},{"_i":"ms_010552.jpg","_t":10552,"_vc":93},{"_i":"ms_010651.jpg","_t":10651,"_vc":93},{"_i":"ms_010750.jpg","_t":10750,"_vc":93},{"_i":"ms_010849.jpg","_t":10849,"_vc":93},{"_i":"ms_010948.jpg","_t":10948,"_vc":93},{"_i":"ms_011053.jpg","_t":11053,"_vc":93},{"_i":"ms_011147.jpg","_t":11147,"_vc":93},{"_i":"ms_011247.jpg","_t":11247,"_vc":93},{"_i":"ms_011345.jpg","_t":11345,"_vc":93},{"_i":"ms_011444.jpg","_t":11444,"_vc":93},{"_i":"ms_011543.jpg","_t":11543,"_vc":93},{"_i":"ms_011642.jpg","_t":11642,"_vc":93},{"_i":"ms_011742.jpg","_t":11742,"_vc":93},{"_i":"ms_011840.jpg","_t":11840,"_vc":93},{"_i":"ms_011939.jpg","_t":11939,"_vc":93},{"_i":"ms_012055.jpg","_t":12055,"_vc":93},{"_i":"ms_012154.jpg","_t":12154,"_vc":93},{"_i":"ms_012253.jpg","_t":12253,"_vc":93},{"_i":"ms_012352.jpg","_t":12352,"_vc":93},{"_i":"ms_012551.jpg","_t":12551,"_vc":93},{"_i":"ms_013046.jpg","_t":13046,"_vc":93},{"_i":"ms_013542.jpg","_t":13542,"_vc":93},{"_i":"ms_014054.jpg","_t":14054,"_vc":93},{"_i":"ms_014550.jpg","_t":14550,"_vc":93},{"_i":"ms_015046.jpg","_t":15046,"_vc":93},{"_i":"ms_015541.jpg","_t":15541,"_vc":93},{"_i":"ms_016052.jpg","_t":16052,"_vc":93},{"_i":"ms_016549.jpg","_t":16549,"_vc":93},{"_i":"ms_017044.jpg","_t":17044,"_vc":93},{"_i":"ms_018060.jpg","_t":18060,"_vc":93},{"_i":"ms_019043.jpg","_t":19043,"_vc":90},{"_i":"ms_020051.jpg","_t":20051,"_vc":90},{"_i":"ms_021045.jpg","_t":21045,"_vc":90},{"_i":"ms_022416.jpg","_t":22416,"_vc":92},{"_i":"ms_027026.jpg","_t":27026,"_vc":100}]],"visualComplete":[20291,27026],"lighthouse":[22,22],"pagespeed":[57,57]}}