{"_ts":[1499156557,1499200080,1499243783],"_r":{"breakdown":{"html":{"bytes":[62734,63013,62903],"requests":[30,31,31]},"js":{"bytes":[1003062,1002690,1002871],"requests":[78,78,78]},"css":{"bytes":[122285,122276,122285],"requests":[9,9,9]},"image":{"bytes":[2291964,2291911,2292140],"requests":[115,115,119]},"flash":{"bytes":[0,0,0],"requests":[0,0,0]},"font":{"bytes":[175704,175704,175704],"requests":[6,6,6]},"other":{"bytes":[66230,66230,66230],"requests":[43,43,43]}},"date":[1499156557,1499200080,1499243783],"domElements":[1536,1536,1536],"domInteractive":[11008,10931,9826],"firstPaint":[9094,9107,8054],"fullyLoaded":[42070,41678,40794],"id":["170704_V8_FYW","170704_02_185P","170705_RV_H3B"],"loadTime":[29964,28838,27835],"render":[9448,9387,8376],"SpeedIndex":[13155,13493,12532],"TTFB":[4382,4732,4017],"videoFrames":[[{"_i":"ms_000000.jpg","_t":0,"_vc":0},{"_i":"ms_009448.jpg","_t":9448,"_vc":24},{"_i":"ms_009468.jpg","_t":9468,"_vc":24},{"_i":"ms_009852.jpg","_t":9852,"_vc":25},{"_i":"ms_010019.jpg","_t":10019,"_vc":25},{"_i":"ms_010860.jpg","_t":10860,"_vc":26},{"_i":"ms_013425.jpg","_t":13425,"_vc":43},{"_i":"ms_014386.jpg","_t":14386,"_vc":66},{"_i":"ms_014969.jpg","_t":14969,"_vc":100},{"_i":"ms_015398.jpg","_t":15398,"_vc":100}],[{"_i":"ms_000000.jpg","_t":0,"_vc":0},{"_i":"ms_009387.jpg","_t":9387,"_vc":25},{"_i":"ms_009420.jpg","_t":9420,"_vc":24},{"_i":"ms_009538.jpg","_t":9538,"_vc":25},{"_i":"ms_010023.jpg","_t":10023,"_vc":25},{"_i":"ms_010378.jpg","_t":10378,"_vc":26},{"_i":"ms_013668.jpg","_t":13668,"_vc":47},{"_i":"ms_014692.jpg","_t":14692,"_vc":65},{"_i":"ms_015659.jpg","_t":15659,"_vc":97},{"_i":"ms_017216.jpg","_t":17216,"_vc":100}],[{"_i":"ms_000000.jpg","_t":0,"_vc":0},{"_i":"ms_008376.jpg","_t":8376,"_vc":25},{"_i":"ms_008395.jpg","_t":8395,"_vc":25},{"_i":"ms_008526.jpg","_t":8526,"_vc":25},{"_i":"ms_009015.jpg","_t":9015,"_vc":25},{"_i":"ms_009405.jpg","_t":9405,"_vc":26},{"_i":"ms_012264.jpg","_t":12264,"_vc":26},{"_i":"ms_012924.jpg","_t":12924,"_vc":43},{"_i":"ms_014287.jpg","_t":14287,"_vc":89},{"_i":"ms_014318.jpg","_t":14318,"_vc":100}]],"visualComplete":[14969,17216,14318],"lighthouse":[27,27,27],"pagespeed":[50,48,51]}}