{"_ts":[1512126988],"_r":{"breakdown":{"html":{"bytes":[55913],"requests":[31]},"js":{"bytes":[1201896],"requests":[77]},"css":{"bytes":[82591],"requests":[9]},"image":{"bytes":[2458606],"requests":[118]},"flash":{"bytes":[0],"requests":[0]},"font":{"bytes":[248468],"requests":[8]},"video":{"bytes":[0],"requests":[0]},"other":{"bytes":[79868],"requests":[48]}},"date":[1512126988],"domElements":[2007],"domInteractive":[3389],"firstPaint":[2965],"fullyLoaded":[10976],"id":["171201_XM_26a931d5b05a1d31feff44ddfba46bc8"],"loadTime":[9291],"render":[3133],"SpeedIndex":[4596],"TTFB":[1950],"videoFrames":[[{"_i":"ms_000000.jpg","_t":0,"_vc":0},{"_i":"ms_003133.jpg","_t":3133,"_vc":47},{"_i":"ms_003267.jpg","_t":3267,"_vc":50},{"_i":"ms_003333.jpg","_t":3333,"_vc":50},{"_i":"ms_003533.jpg","_t":3533,"_vc":50},{"_i":"ms_003600.jpg","_t":3600,"_vc":50},{"_i":"ms_003633.jpg","_t":3633,"_vc":52},{"_i":"ms_003700.jpg","_t":3700,"_vc":51},{"_i":"ms_003767.jpg","_t":3767,"_vc":59},{"_i":"ms_003967.jpg","_t":3967,"_vc":59},{"_i":"ms_005033.jpg","_t":5033,"_vc":59},{"_i":"ms_005100.jpg","_t":5100,"_vc":60},{"_i":"ms_005333.jpg","_t":5333,"_vc":70},{"_i":"ms_005867.jpg","_t":5867,"_vc":70},{"_i":"ms_006467.jpg","_t":6467,"_vc":77},{"_i":"ms_007167.jpg","_t":7167,"_vc":100},{"_i":"ms_010033.jpg","_t":10033,"_vc":99},{"_i":"ms_010333.jpg","_t":10333,"_vc":99},{"_i":"ms_010367.jpg","_t":10367,"_vc":99},{"_i":"ms_010400.jpg","_t":10400,"_vc":100},{"_i":"ms_010433.jpg","_t":10433,"_vc":100},{"_i":"ms_010500.jpg","_t":10500,"_vc":100}]],"visualComplete":[7167],"lighthouse":[45],"pagespeed":[63]}}