{"_ts":[1496307153,1496351198,1496395294],"_r":{"breakdown":{"html":{"bytes":[65485,108887,65567],"requests":[22,24,22]},"js":{"bytes":[951008,954496,952604],"requests":[69,69,69]},"css":{"bytes":[117506,119075,119087],"requests":[8,8,8]},"image":{"bytes":[221320,221505,221320],"requests":[49,53,49]},"flash":{"bytes":[0,0,0],"requests":[0,0,0]},"font":{"bytes":[175704,175704,175704],"requests":[6,6,6]},"other":{"bytes":[25769,25769,25769],"requests":[37,36,37]}},"date":[1496307153,1496351198,1496395294],"domElements":[1083,1084,1084],"domInteractive":[10369,10361,10424],"firstPaint":[8035,7923,7873],"fullyLoaded":[31975,40441,30737],"id":["170601_GD_HC5","170601_ZT_1G98","170602_A0_MMK"],"loadTime":[17990,28022,18909],"render":[10322,10258,10112],"SpeedIndex":[10390,10297,10169],"TTFB":[2689,2631,2836],"videoFrames":[[{"_i":"ms_000000.jpg","_t":0,"_vc":0},{"_i":"ms_010322.jpg","_t":10322,"_vc":80},{"_i":"ms_010354.jpg","_t":10354,"_vc":92},{"_i":"ms_010517.jpg","_t":10517,"_vc":92},{"_i":"ms_010616.jpg","_t":10616,"_vc":94},{"_i":"ms_011295.jpg","_t":11295,"_vc":100}],[{"_i":"ms_000000.jpg","_t":0,"_vc":0},{"_i":"ms_010258.jpg","_t":10258,"_vc":92},{"_i":"ms_010426.jpg","_t":10426,"_vc":92},{"_i":"ms_010561.jpg","_t":10561,"_vc":94},{"_i":"ms_010813.jpg","_t":10813,"_vc":100}],[{"_i":"ms_000000.jpg","_t":0,"_vc":0},{"_i":"ms_010112.jpg","_t":10112,"_vc":80},{"_i":"ms_010174.jpg","_t":10174,"_vc":92},{"_i":"ms_010427.jpg","_t":10427,"_vc":92},{"_i":"ms_010527.jpg","_t":10527,"_vc":94},{"_i":"ms_010814.jpg","_t":10814,"_vc":100}]],"visualComplete":[11295,10813,10814],"lighthouse":[27,27,27],"pagespeed":[70,69,70]}}