{"_ts":[1514805446,1514849402],"_r":{"breakdown":{"html":{"bytes":[74916,63470],"requests":[16,18]},"js":{"bytes":[906770,941244],"requests":[59,59]},"css":{"bytes":[48009,38853],"requests":[6,6]},"image":{"bytes":[1566477,1577893],"requests":[69,70]},"flash":{"bytes":[0,0],"requests":[0,0]},"font":{"bytes":[353367,353798],"requests":[6,6]},"video":{"bytes":[0,0],"requests":[0,0]},"other":{"bytes":[16751,16796],"requests":[37,38]}},"date":[1514805446,1514849402],"domElements":[912,913],"domInteractive":[2575,2429],"firstPaint":[2398,2265],"fullyLoaded":[6636,9062],"id":["180101_6E_e0bf31933d4444577c70c6bb0bbff5b8","180101_35_96776a86f41760481a356e85ea07f4ad"],"loadTime":[4800,4669],"render":[2533,2433],"SpeedIndex":[3077,2759],"TTFB":[505,232],"videoFrames":[[{"_i":"ms_000000.jpg","_t":0,"_vc":0},{"_i":"ms_002533.jpg","_t":2533,"_vc":34},{"_i":"ms_002633.jpg","_t":2633,"_vc":49},{"_i":"ms_002700.jpg","_t":2700,"_vc":52},{"_i":"ms_002800.jpg","_t":2800,"_vc":55},{"_i":"ms_003633.jpg","_t":3633,"_vc":99},{"_i":"ms_003833.jpg","_t":3833,"_vc":100},{"_i":"ms_004567.jpg","_t":4567,"_vc":99},{"_i":"ms_004800.jpg","_t":4800,"_vc":100},{"_i":"ms_005067.jpg","_t":5067,"_vc":99},{"_i":"ms_005300.jpg","_t":5300,"_vc":99},{"_i":"ms_005567.jpg","_t":5567,"_vc":99},{"_i":"ms_005833.jpg","_t":5833,"_vc":100},{"_i":"ms_006067.jpg","_t":6067,"_vc":99},{"_i":"ms_006333.jpg","_t":6333,"_vc":99},{"_i":"ms_006567.jpg","_t":6567,"_vc":99},{"_i":"ms_006967.jpg","_t":6967,"_vc":100},{"_i":"ms_007033.jpg","_t":7033,"_vc":100},{"_i":"ms_007100.jpg","_t":7100,"_vc":100}],[{"_i":"ms_000000.jpg","_t":0,"_vc":0},{"_i":"ms_002433.jpg","_t":2433,"_vc":34},{"_i":"ms_002533.jpg","_t":2533,"_vc":62},{"_i":"ms_002633.jpg","_t":2633,"_vc":62},{"_i":"ms_003200.jpg","_t":3200,"_vc":99},{"_i":"ms_003367.jpg","_t":3367,"_vc":99},{"_i":"ms_003400.jpg","_t":3400,"_vc":100},{"_i":"ms_004467.jpg","_t":4467,"_vc":100},{"_i":"ms_004733.jpg","_t":4733,"_vc":100},{"_i":"ms_004967.jpg","_t":4967,"_vc":100},{"_i":"ms_005233.jpg","_t":5233,"_vc":99},{"_i":"ms_005467.jpg","_t":5467,"_vc":100},{"_i":"ms_005733.jpg","_t":5733,"_vc":99},{"_i":"ms_005967.jpg","_t":5967,"_vc":100},{"_i":"ms_006233.jpg","_t":6233,"_vc":100},{"_i":"ms_006500.jpg","_t":6500,"_vc":100}]],"visualComplete":[3833,3400],"lighthouse":[54,54],"pagespeed":[60,60]}}