{"_ts":[1533108530],"_r":{"breakdown":{"html":{"bytes":[39467],"requests":[16]},"js":{"bytes":[776498],"requests":[56]},"css":{"bytes":[29856],"requests":[7]},"image":{"bytes":[3733130],"requests":[49]},"flash":{"bytes":[0],"requests":[0]},"font":{"bytes":[168218],"requests":[4]},"video":{"bytes":[0],"requests":[0]},"other":{"bytes":[26484],"requests":[28]}},"date":[1533108530],"domElements":[1254],"domInteractive":[3295],"firstPaint":[2334.5999999983],"fullyLoaded":[10640],"id":["180801_ZN_59e0a943eb9cf7c6d6c82323795ed9d1"],"loadTime":[9386],"render":[2400],"SpeedIndex":[7861],"TTFB":[687],"videoFrames":[[{"_i":"ms_000000.jpg","_t":0,"_vc":0},{"_i":"ms_002400.jpg","_t":2400,"_vc":18},{"_i":"ms_002500.jpg","_t":2500,"_vc":18},{"_i":"ms_002700.jpg","_t":2700,"_vc":20},{"_i":"ms_002900.jpg","_t":2900,"_vc":20},{"_i":"ms_003400.jpg","_t":3400,"_vc":20},{"_i":"ms_003700.jpg","_t":3700,"_vc":20},{"_i":"ms_004800.jpg","_t":4800,"_vc":21},{"_i":"ms_006300.jpg","_t":6300,"_vc":21},{"_i":"ms_006700.jpg","_t":6700,"_vc":21},{"_i":"ms_007300.jpg","_t":7300,"_vc":21},{"_i":"ms_007700.jpg","_t":7700,"_vc":36},{"_i":"ms_008700.jpg","_t":8700,"_vc":52},{"_i":"ms_009000.jpg","_t":9000,"_vc":56},{"_i":"ms_009100.jpg","_t":9100,"_vc":56},{"_i":"ms_009400.jpg","_t":9400,"_vc":56},{"_i":"ms_009700.jpg","_t":9700,"_vc":56},{"_i":"ms_009900.jpg","_t":9900,"_vc":36},{"_i":"ms_010000.jpg","_t":10000,"_vc":100}]],"visualComplete":[10000],"lighthouse":[31],"pagespeed":[31]}}