{"_ts":[1509499710,1509542893],"_r":{"breakdown":{"html":{"bytes":[38915,38914],"requests":[14,14]},"js":{"bytes":[320945,320887],"requests":[34,35]},"css":{"bytes":[26199,26199],"requests":[6,6]},"image":{"bytes":[177080,177634],"requests":[34,37]},"flash":{"bytes":[0,0],"requests":[0,0]},"font":{"bytes":[191392,191392],"requests":[5,5]},"video":{"bytes":[0,0],"requests":[0,0]},"other":{"bytes":[2018,2018],"requests":[17,15]}},"date":[1509499710,1509542893],"domElements":[780,780],"domInteractive":[753,688],"firstPaint":[674,620],"fullyLoaded":[3528,5271],"id":["171101_JD_ff6155ac68233aff21658f4027ca9a66","171101_54_0dcf2bce5b46b719c3122fc50dadad9f"],"loadTime":[1898,3631],"render":[1067,1000],"SpeedIndex":[1086,1043],"TTFB":[314,275],"videoFrames":[[{"_i":"ms_000000.jpg","_t":0,"_vc":0},{"_i":"ms_001067.jpg","_t":1067,"_vc":99},{"_i":"ms_001500.jpg","_t":1500,"_vc":99},{"_i":"ms_001767.jpg","_t":1767,"_vc":100},{"_i":"ms_002000.jpg","_t":2000,"_vc":99},{"_i":"ms_002267.jpg","_t":2267,"_vc":99},{"_i":"ms_002500.jpg","_t":2500,"_vc":99},{"_i":"ms_002767.jpg","_t":2767,"_vc":99},{"_i":"ms_003233.jpg","_t":3233,"_vc":100},{"_i":"ms_003267.jpg","_t":3267,"_vc":100}],[{"_i":"ms_000000.jpg","_t":0,"_vc":0},{"_i":"ms_001000.jpg","_t":1000,"_vc":99},{"_i":"ms_001500.jpg","_t":1500,"_vc":99},{"_i":"ms_001733.jpg","_t":1733,"_vc":99},{"_i":"ms_001967.jpg","_t":1967,"_vc":99},{"_i":"ms_002233.jpg","_t":2233,"_vc":99},{"_i":"ms_002467.jpg","_t":2467,"_vc":99},{"_i":"ms_002733.jpg","_t":2733,"_vc":99},{"_i":"ms_002967.jpg","_t":2967,"_vc":99},{"_i":"ms_003667.jpg","_t":3667,"_vc":99},{"_i":"ms_003733.jpg","_t":3733,"_vc":99},{"_i":"ms_004000.jpg","_t":4000,"_vc":99},{"_i":"ms_004233.jpg","_t":4233,"_vc":99},{"_i":"ms_004467.jpg","_t":4467,"_vc":99},{"_i":"ms_004733.jpg","_t":4733,"_vc":99},{"_i":"ms_005033.jpg","_t":5033,"_vc":99},{"_i":"ms_005300.jpg","_t":5300,"_vc":100},{"_i":"ms_005333.jpg","_t":5333,"_vc":100}]],"visualComplete":[1767,5300],"lighthouse":[54,54],"pagespeed":[75,74]}}