{"_ts":[1499156123,1499200038,1499243756],"_r":{"breakdown":{"html":{"bytes":[82492,80568,82650],"requests":[44,37,44]},"js":{"bytes":[1232128,1229454,1293401],"requests":[79,75,77]},"css":{"bytes":[32644,36004,30041],"requests":[12,12,10]},"image":{"bytes":[759223,924066,606530],"requests":[96,106,104]},"flash":{"bytes":[0,0,0],"requests":[0,0,0]},"font":{"bytes":[186705,177040,196361],"requests":[8,7,9]},"other":{"bytes":[35537,35538,35537],"requests":[49,51,51]}},"date":[1499156123,1499200038,1499243756],"domElements":[1249,1248,1250],"domInteractive":[7095,6033,5905],"firstPaint":[5914,4736,4780],"fullyLoaded":[36692,36050,36222],"id":["170704_22_FP4","170704_JA_1860","170705_9G_H3K"],"loadTime":[24041,23477,23144],"render":[6171,4977,5019],"SpeedIndex":[6773,5413,5577],"TTFB":[2236,1071,1078],"videoFrames":[[{"_i":"ms_000000.jpg","_t":0,"_vc":0},{"_i":"ms_006171.jpg","_t":6171,"_vc":80},{"_i":"ms_006188.jpg","_t":6188,"_vc":79},{"_i":"ms_006253.jpg","_t":6253,"_vc":79},{"_i":"ms_006320.jpg","_t":6320,"_vc":79},{"_i":"ms_006456.jpg","_t":6456,"_vc":80},{"_i":"ms_006699.jpg","_t":6699,"_vc":85},{"_i":"ms_006765.jpg","_t":6765,"_vc":97},{"_i":"ms_007243.jpg","_t":7243,"_vc":98},{"_i":"ms_013771.jpg","_t":13771,"_vc":97},{"_i":"ms_015748.jpg","_t":15748,"_vc":98},{"_i":"ms_015963.jpg","_t":15963,"_vc":98},{"_i":"ms_016805.jpg","_t":16805,"_vc":97},{"_i":"ms_017152.jpg","_t":17152,"_vc":97},{"_i":"ms_019978.jpg","_t":19978,"_vc":99},{"_i":"ms_020015.jpg","_t":20015,"_vc":99},{"_i":"ms_020105.jpg","_t":20105,"_vc":100},{"_i":"ms_020216.jpg","_t":20216,"_vc":99},{"_i":"ms_020303.jpg","_t":20303,"_vc":99},{"_i":"ms_020412.jpg","_t":20412,"_vc":99},{"_i":"ms_020516.jpg","_t":20516,"_vc":99},{"_i":"ms_023991.jpg","_t":23991,"_vc":99},{"_i":"ms_024010.jpg","_t":24010,"_vc":99},{"_i":"ms_024505.jpg","_t":24505,"_vc":99},{"_i":"ms_027987.jpg","_t":27987,"_vc":99},{"_i":"ms_028006.jpg","_t":28006,"_vc":99},{"_i":"ms_028506.jpg","_t":28506,"_vc":99},{"_i":"ms_031967.jpg","_t":31967,"_vc":99},{"_i":"ms_032019.jpg","_t":32019,"_vc":99},{"_i":"ms_032511.jpg","_t":32511,"_vc":99},{"_i":"ms_035985.jpg","_t":35985,"_vc":99},{"_i":"ms_036003.jpg","_t":36003,"_vc":99},{"_i":"ms_036495.jpg","_t":36495,"_vc":100}],[{"_i":"ms_000000.jpg","_t":0,"_vc":0},{"_i":"ms_004977.jpg","_t":4977,"_vc":80},{"_i":"ms_004995.jpg","_t":4995,"_vc":79},{"_i":"ms_005013.jpg","_t":5013,"_vc":79},{"_i":"ms_005180.jpg","_t":5180,"_vc":80},{"_i":"ms_005325.jpg","_t":5325,"_vc":81},{"_i":"ms_005507.jpg","_t":5507,"_vc":85},{"_i":"ms_005590.jpg","_t":5590,"_vc":97},{"_i":"ms_007860.jpg","_t":7860,"_vc":98},{"_i":"ms_011794.jpg","_t":11794,"_vc":98},{"_i":"ms_011951.jpg","_t":11951,"_vc":98},{"_i":"ms_013277.jpg","_t":13277,"_vc":97},{"_i":"ms_014568.jpg","_t":14568,"_vc":98},{"_i":"ms_015166.jpg","_t":15166,"_vc":99},{"_i":"ms_015533.jpg","_t":15533,"_vc":99},{"_i":"ms_016076.jpg","_t":16076,"_vc":99},{"_i":"ms_016176.jpg","_t":16176,"_vc":99},{"_i":"ms_016259.jpg","_t":16259,"_vc":99},{"_i":"ms_016326.jpg","_t":16326,"_vc":99},{"_i":"ms_016416.jpg","_t":16416,"_vc":99},{"_i":"ms_016509.jpg","_t":16509,"_vc":99},{"_i":"ms_016691.jpg","_t":16691,"_vc":99},{"_i":"ms_019358.jpg","_t":19358,"_vc":99},{"_i":"ms_019891.jpg","_t":19891,"_vc":99},{"_i":"ms_019921.jpg","_t":19921,"_vc":99},{"_i":"ms_020005.jpg","_t":20005,"_vc":99},{"_i":"ms_020104.jpg","_t":20104,"_vc":99},{"_i":"ms_020203.jpg","_t":20203,"_vc":100},{"_i":"ms_020319.jpg","_t":20319,"_vc":100},{"_i":"ms_023652.jpg","_t":23652,"_vc":100},{"_i":"ms_023715.jpg","_t":23715,"_vc":100},{"_i":"ms_023849.jpg","_t":23849,"_vc":99},{"_i":"ms_023904.jpg","_t":23904,"_vc":99},{"_i":"ms_024001.jpg","_t":24001,"_vc":99},{"_i":"ms_027430.jpg","_t":27430,"_vc":99},{"_i":"ms_027576.jpg","_t":27576,"_vc":99},{"_i":"ms_027609.jpg","_t":27609,"_vc":99},{"_i":"ms_027942.jpg","_t":27942,"_vc":100}],[{"_i":"ms_000000.jpg","_t":0,"_vc":0},{"_i":"ms_005019.jpg","_t":5019,"_vc":77},{"_i":"ms_005054.jpg","_t":5054,"_vc":77},{"_i":"ms_005098.jpg","_t":5098,"_vc":77},{"_i":"ms_005368.jpg","_t":5368,"_vc":82},{"_i":"ms_005485.jpg","_t":5485,"_vc":94},{"_i":"ms_005552.jpg","_t":5552,"_vc":94},{"_i":"ms_005637.jpg","_t":5637,"_vc":96},{"_i":"ms_011640.jpg","_t":11640,"_vc":96},{"_i":"ms_013109.jpg","_t":13109,"_vc":94},{"_i":"ms_013496.jpg","_t":13496,"_vc":95},{"_i":"ms_015384.jpg","_t":15384,"_vc":95},{"_i":"ms_015641.jpg","_t":15641,"_vc":97},{"_i":"ms_015658.jpg","_t":15658,"_vc":97},{"_i":"ms_016168.jpg","_t":16168,"_vc":97},{"_i":"ms_016249.jpg","_t":16249,"_vc":100}]],"visualComplete":[20105,20203,16249],"lighthouse":[27,null,27],"pagespeed":[58,54,61]}}